daemonize.py
daemonize-2.4.7.dist-info/DESCRIPTION.rst
daemonize-2.4.7.dist-info/METADATA
daemonize-2.4.7.dist-info/RECORD
daemonize-2.4.7.dist-info/WHEEL
daemonize-2.4.7.dist-info/metadata.json
daemonize-2.4.7.dist-info/top_level.txt
